yieldflow/__init__.py
yieldflow/pipelines.py
yieldflow/processors.py
yieldflow-0.1.1.dist-info/licenses/LICENSE.bak
yieldflow-0.1.1.dist-info/METADATA
yieldflow-0.1.1.dist-info/WHEEL
yieldflow-0.1.1.dist-info/top_level.txt
yieldflow-0.1.1.dist-info/RECORD
